azureml/__init__.py
azureml/responsibleai/__init__.py
azureml/responsibleai/_version.py
azureml/responsibleai/common/__init__.py
azureml/responsibleai/common/_constants.py
azureml/responsibleai/common/_loggerfactory.py
azureml/responsibleai/common/_search_assets.py
azureml/responsibleai/common/model_loader.py
azureml/responsibleai/common/pickle_model_loader.py
azureml/responsibleai/common/rai_artifact_client.py
azureml/responsibleai/common/rai_validations.py
azureml/responsibleai/common/_errors/__init__.py
azureml/responsibleai/common/_errors/error_definitions.py
azureml/responsibleai/common/_errors/error_strings.py
azureml/responsibleai/model/__init__.py
azureml/responsibleai/model/model_serializer.py
azureml/responsibleai/model/pyfunc_model.py
azureml/responsibleai/tools/__init__.py
azureml/responsibleai/tools/_causal/__init__.py
azureml/responsibleai/tools/_causal/causal_client.py
azureml/responsibleai/tools/_causal/causal_manager.py
azureml/responsibleai/tools/_causal/causal_output_v0.0.json
azureml/responsibleai/tools/_causal/causal_output_v1.0.json
azureml/responsibleai/tools/_causal/causal_output_v2.0.json
azureml/responsibleai/tools/_common/__init__.py
azureml/responsibleai/tools/_common/base_manager.py
azureml/responsibleai/tools/_common/base_request.py
azureml/responsibleai/tools/_common/constants.py
azureml/responsibleai/tools/_counterfactual/__init__.py
azureml/responsibleai/tools/_counterfactual/counterfactual_client.py
azureml/responsibleai/tools/_counterfactual/counterfactual_examples_output_v1.0.json
azureml/responsibleai/tools/_counterfactual/counterfactual_examples_output_v2.0.json
azureml/responsibleai/tools/_counterfactual/counterfactual_manager.py
azureml/responsibleai/tools/_error_analysis/__init__.py
azureml/responsibleai/tools/_error_analysis/error_analysis_client.py
azureml/responsibleai/tools/_error_analysis/error_analysis_manager.py
azureml/responsibleai/tools/_error_analysis/error_analysis_output_v0.0.json
azureml_responsibleai-1.60.0.dist-info/licenses/LICENSE.txt
azureml_responsibleai-1.60.0.dist-info/METADATA
azureml_responsibleai-1.60.0.dist-info/WHEEL
azureml_responsibleai-1.60.0.dist-info/namespace_packages.txt
azureml_responsibleai-1.60.0.dist-info/top_level.txt
azureml_responsibleai-1.60.0.dist-info/RECORD
