Metadata-Version: 2.4
Name: azureml-responsibleai
Version: 1.60.0
Summary: AzureML Responsible AI package
Home-page: https://docs.microsoft.com/python/api/overview/azure/ml/?view=azure-ml-py
Author: Microsoft Corp
Author-email: amlraidev@microsoft.com
License: Proprietary https://aka.ms/azureml-preview-sdk-license 
Classifier: Intended Audience :: Developers
Classifier: Intended Audience :: Science/Research
Classifier: License :: Other/Proprietary License
Classifier: Programming Language :: Python :: 3
Classifier: Programming Language :: Python :: 3.8
Classifier: Programming Language :: Python :: 3.9
Classifier: Programming Language :: Python :: 3.10
Classifier: Programming Language :: Python :: 3.11
Classifier: Topic :: Scientific/Engineering :: Artificial Intelligence
Classifier: Operating System :: Microsoft :: Windows
Classifier: Operating System :: MacOS
Classifier: Operating System :: POSIX :: Linux
Requires-Python: >=3.8,<3.12
License-File: LICENSE.txt
Requires-Dist: azureml-core~=1.60.0
Requires-Dist: azureml-dataset-runtime~=1.60.0
Requires-Dist: azureml-telemetry~=1.60.0
Requires-Dist: azureml-interpret~=1.60.0
Requires-Dist: fairlearn==0.7.0
Requires-Dist: joblib
Requires-Dist: jsonschema
Requires-Dist: responsibleai==0.36.0
Dynamic: author
Dynamic: author-email
Dynamic: classifier
Dynamic: description
Dynamic: description-content-type
Dynamic: home-page
Dynamic: license
Dynamic: license-file
Dynamic: requires-dist
Dynamic: requires-python
Dynamic: summary
